{
  "generated_at": "2026-07-20T18:29:54Z",
  "stale": true,
  "sources": {
    "tw_revenue": {
      "status": "stale",
      "last_updated": "2026-07-20T16:09:26Z",
      "source": "previous latest.json",
      "missing": [],
      "notes": [
        "market-only update: fundamental component carried forward"
      ]
    },
    "sec_capex": {
      "status": "stale",
      "last_updated": "2026-07-20T16:09:26Z",
      "source": "previous latest.json",
      "missing": [],
      "notes": [
        "market-only update: fundamental component carried forward"
      ]
    },
    "market_prices": {
      "status": "ok",
      "last_updated": "2026-07-20T18:29:45Z",
      "source": "Stooq / Yahoo Finance chart / Nasdaq historical",
      "success_count": 10,
      "missing": [],
      "notes": []
    }
  }
}
